deltaguard/__init__.py
deltaguard/adapter.py
deltaguard/extension.py
scrapy_delta_guard-0.0.8.dist-info/METADATA
scrapy_delta_guard-0.0.8.dist-info/WHEEL
scrapy_delta_guard-0.0.8.dist-info/top_level.txt
scrapy_delta_guard-0.0.8.dist-info/RECORD
